multidb_mcp_client/__init__.py
multidb_mcp_client/server.py
multidb_mcp_client/resources/db_resources.py
multidb_mcp_client/tools/db_tool.py
multidb_mcp_client/utils/__init__.py
multidb_mcp_client/utils/db_config.py
multidb_mcp_client/utils/db_operate.py
multidb_mcp_client/utils/http_util.py
multidb_mcp_client/utils/logger_util.py
multidb_mcp_client-1.0.9.dist-info/METADATA
multidb_mcp_client-1.0.9.dist-info/WHEEL
multidb_mcp_client-1.0.9.dist-info/entry_points.txt
multidb_mcp_client-1.0.9.dist-info/top_level.txt
multidb_mcp_client-1.0.9.dist-info/RECORD
