Metadata-Version: 2.4
Name: multidb-mcp-client
Version: 1.0.9
Summary: A Model Context Protocol (MCP) server that enables secure interaction with MySQL/MariaDB/TiDB/AWS OceanBase/RDS/Aurora MySQL DataBases.
Author-email: Frank Jin <j00131120@163.com>
Maintainer-email: Frank Jin <j00131120@163.com>
License: MIT
Project-URL: Homepage, https://github.com/j00131120/mcp_database_server/tree/main/multidb_mcp_client
Project-URL: Documentation, https://github.com/j00131120/mcp_database_server/blob/main/multidb_mcp_client/README.md
Project-URL: Repository, https://github.com/j00131120/mcp_database_server.git
Project-URL: Bug Tracker, https://github.com/j00131120/mcp_database_server/issues
Project-URL: Source Code, https://github.com/j00131120/mcp_database_server/tree/main/multidb_mcp_client
Project-URL: Download, https://github.com/j00131120/mcp_database_server/tree/main/multidb_mcp_client
Project-URL: Changelog, https://github.com/j00131120/mcp_database_server/blob/main/multidb_mcp_client/CHANGELOG.md
Keywords: mcp,mysql,tidb,oceanbase,xesql,ubisql,rasesql,model-context-protocol,async,connection-pool
Classifier: Development Status :: 5 - Production/Stable
Classifier: Intended Audience :: Developers
Classifier: Operating System :: OS Independent
Classifier: Programming Language :: Python :: 3
Classifier: Programming Language :: Python :: 3.12
Classifier: Topic :: Database
Classifier: Topic :: Software Development :: Libraries :: Python Modules
Classifier: Framework :: AsyncIO
Requires-Python: >=3.12
Requires-Dist: aiohttp>=3.12.15
Requires-Dist: aiomysql>=0.2.0
Requires-Dist: fastmcp>=2.11.2
Requires-Dist: loguru>=0.7.3
Requires-Dist: mcp[cli]>=1.12.4
